.gitattributes
.gitignore
.gitmodules
CHANGELOG.md
LICENSE
MANIFEST.in
README.md
requirements.txt
setup.py
.github/FUNDING.yml
.github/workflows/python-publish.yaml
.github/workflows/test.yaml
SudachiTra.egg-info/PKG-INFO
SudachiTra.egg-info/SOURCES.txt
SudachiTra.egg-info/dependency_links.txt
SudachiTra.egg-info/requires.txt
SudachiTra.egg-info/top_level.txt
evaluation/README.md
evaluation/install_jumanpp.sh
evaluation/summary_results.py
evaluation/jglue/README.md
evaluation/jglue/requirements.txt
evaluation/jglue/transformers-4.26.1_jglue-1.1.0_chitra-0.1.8.patch
evaluation/pytorch/classification_utils.py
evaluation/pytorch/convert_dataset.py
evaluation/pytorch/multiple_choice_utils.py
evaluation/pytorch/qa_utils.py
evaluation/pytorch/requirements.txt
evaluation/pytorch/run_all.sh
evaluation/pytorch/run_evaluation.py
evaluation/pytorch/tokenizer_utils.py
evaluation/tensorflow/classification_utils.py
evaluation/tensorflow/convert_dataset.py
evaluation/tensorflow/multiple_choice_utils.py
evaluation/tensorflow/qa_utils.py
evaluation/tensorflow/requirements.txt
evaluation/tensorflow/run_all.sh
evaluation/tensorflow/run_evaluation.py
evaluation/tensorflow/tokenizer_utils.py
misc/license-header.txt
pretraining/bert/README.md
pretraining/bert/__init__.py
pretraining/bert/convert_original_tf2_checkpoint_to_pytorch_nvidia.py
pretraining/bert/prepare_dataset.py
pretraining/bert/preprocess_dataset.py
pretraining/bert/requirements.txt
pretraining/bert/run_create_pretraining_data.sh
pretraining/bert/run_prepare_dataset.sh
pretraining/bert/split_dataset.py
pretraining/bert/train_pos_substitution_tokenizer.py
pretraining/bert/train_wordpiece_tokenizer.py
pretraining/bert/corpus_preprocessing/__init__.py
pretraining/bert/corpus_preprocessing/filter/__init__.py
pretraining/bert/corpus_preprocessing/filter/document_filter/__init__.py
pretraining/bert/corpus_preprocessing/filter/document_filter/document_filter.py
pretraining/bert/corpus_preprocessing/filter/document_filter/document_filter_name.py
pretraining/bert/corpus_preprocessing/filter/sentence_filter/__init__.py
pretraining/bert/corpus_preprocessing/filter/sentence_filter/sentence_filter.py
