Metadata-Version: 2.1
Name: SudachiTra
Version: 0.1.9
Summary: Japanese tokenizer for Transformers.
Home-page: https://github.com/WorksApplications/SudachiTra
Author: Works Applications
Author-email: sudachi@worksap.co.jp
License: Apache-2.0
License-File: LICENSE
Requires-Dist: logzero~=1.7.0
Requires-Dist: tokenizers>=0.10.3
Requires-Dist: transformers>=4.6.1
Requires-Dist: sudachipy>=0.6.2
Requires-Dist: sudachidict_core>=20210802
Provides-Extra: pretrain
Requires-Dist: progressbar2~=3.53.1; extra == "pretrain"
Requires-Dist: bunkai~=1.4.3; extra == "pretrain"
Requires-Dist: pytextspan>=0.5.4; extra == "pretrain"
Requires-Dist: tensorflow>=2.5.0; extra == "pretrain"
Requires-Dist: tensorflow_datasets>=4.3.0; extra == "pretrain"
